vbtikztoanimation/__init__.py
vbtikztoanimation/__main__.py
vbtikztoanimation/choice_option.py
vbtikztoanimation/extracttikz.py
vbtikztoanimation/genframes.py
vbtikztoanimation/main.py
vbtikztoanimation/renderanimation.py
vbtikztoanimation/renderframes.py
vbtikztoanimation-0.1.1.dist-info/METADATA
vbtikztoanimation-0.1.1.dist-info/WHEEL
vbtikztoanimation-0.1.1.dist-info/entry_points.txt
vbtikztoanimation-0.1.1.dist-info/RECORD
